yib/__init__.py
yib/_version.py
yib/yconsole.py
yib-0.3.0.dist-info/METADATA
yib-0.3.0.dist-info/WHEEL
yib-0.3.0.dist-info/licenses/LICENSE
yib-0.3.0.dist-info/RECORD
