Metadata-Version: 2.4
Name: yib
Version: 0.3.0
Summary: yib is one Python utility library.
Project-URL: Home, https://github.com/mangoumbrella/yib
Project-URL: Source, https://github.com/mangoumbrella/yib
Author-email: Mango Umbrella LLC <hi@mangoumbrella.com>
License-Expression: Apache-2.0
License-File: LICENSE
Keywords: utility
Classifier: Development Status :: 4 - Beta
Classifier: Intended Audience :: Developers
Classifier: Operating System :: OS Independent
Classifier: Programming Language :: Python
Classifier: Programming Language :: Python :: 3 :: Only
Classifier: Programming Language :: Python :: 3.10
Classifier: Programming Language :: Python :: 3.11
Classifier: Programming Language :: Python :: 3.12
Classifier: Programming Language :: Python :: 3.13
Classifier: Programming Language :: Python :: 3.14
Classifier: Topic :: Utilities
Requires-Python: >=3.10
Requires-Dist: rich>=13.0.0
